cfbd_mcp_server/__init__.py
cfbd_mcp_server/__main__.py
cfbd_mcp_server/cfbd_schema.py
cfbd_mcp_server/sample.env
cfbd_mcp_server/schema_helpers.py
cfbd_mcp_server/server.py
iflow_mcp_cfbd_mcp_server-0.5.0.dist-info/METADATA
iflow_mcp_cfbd_mcp_server-0.5.0.dist-info/WHEEL
iflow_mcp_cfbd_mcp_server-0.5.0.dist-info/entry_points.txt
iflow_mcp_cfbd_mcp_server-0.5.0.dist-info/licenses/LICENSE
iflow_mcp_cfbd_mcp_server-0.5.0.dist-info/RECORD
