Metadata-Version: 2.4
Name: iflow-mcp_cfbd-mcp-server
Version: 0.5.0
Summary: Interact with the College Football Data API via the Claude Desktop.
Author: Chris Leonard
License-File: LICENSE
Requires-Python: >=3.11
Requires-Dist: mcp>=1.1.2
Requires-Dist: python-dotenv>=1.0.1
